cogeo_mosaic/__init__.py
cogeo_mosaic/cache.py
cogeo_mosaic/errors.py
cogeo_mosaic/logger.py
cogeo_mosaic/models.py
cogeo_mosaic/mosaic.py
cogeo_mosaic/py.typed
cogeo_mosaic/utils.py
cogeo_mosaic/backends/__init__.py
cogeo_mosaic/backends/az.py
cogeo_mosaic/backends/base.py
cogeo_mosaic/backends/dynamodb.py
cogeo_mosaic/backends/file.py
cogeo_mosaic/backends/gs.py
cogeo_mosaic/backends/memory.py
cogeo_mosaic/backends/s3.py
cogeo_mosaic/backends/sqlite.py
cogeo_mosaic/backends/stac.py
cogeo_mosaic/backends/utils.py
cogeo_mosaic/backends/web.py
cogeo_mosaic/scripts/__init__.py
cogeo_mosaic/scripts/cli.py
cogeo_mosaic-9.0.2.dist-info/METADATA
cogeo_mosaic-9.0.2.dist-info/WHEEL
cogeo_mosaic-9.0.2.dist-info/entry_points.txt
cogeo_mosaic-9.0.2.dist-info/licenses/LICENSE
cogeo_mosaic-9.0.2.dist-info/RECORD
