Metadata-Version: 2.4
Name: cogeo-mosaic
Version: 9.0.2
Summary: CLI and Backends to work with MosaicJSON.
Project-URL: Homepage, https://github.com/developmentseed/cogeo-mosaic
Project-URL: Documentation, https://developmentseed.org/cogeo-mosaic/
Project-URL: Issues, https://github.com/developmentseed/cogeo-mosaic/issues
Project-URL: Source, https://github.com/developmentseed/cogeo-mosaic
Project-URL: Changelog, https://developmentseed.org/cogeo-mosaic/release-notes/
Author-email: Vincent Sarago <vincent@developmentseed.com>
License: MIT License
License-File: LICENSE
Keywords: COG,MosaicJSON
Classifier: Intended Audience :: Information Technology
Classifier: Intended Audience :: Science/Research
Classifier: License :: OSI Approved :: MIT License
Classifier: Programming Language :: Python :: 3
Classifier: Programming Language :: Python :: 3 :: Only
Classifier: Programming Language :: Python :: 3.11
Classifier: Programming Language :: Python :: 3.12
Classifier: Programming Language :: Python :: 3.13
Classifier: Programming Language :: Python :: 3.14
Classifier: Topic :: Scientific/Engineering :: GIS
Requires-Python: >=3.11
Requires-Dist: attrs
Requires-Dist: cachetools
Requires-Dist: click
Requires-Dist: click-plugins
Requires-Dist: cligj
Requires-Dist: httpx
Requires-Dist: morecantile>=7.0
Requires-Dist: numpy
Requires-Dist: pydantic-settings~=2.0
Requires-Dist: pydantic~=2.0
Requires-Dist: rasterio
Requires-Dist: rio-tiler<9.0,>=8.0
Requires-Dist: shapely<3.0,>=2.0
Requires-Dist: supermorecado
Provides-Extra: aws
Requires-Dist: boto3; extra == 'aws'
Provides-Extra: az
Requires-Dist: azure-identity; extra == 'az'
Requires-Dist: azure-storage-blob; extra == 'az'
Provides-Extra: gcp
Requires-Dist: google-cloud-storage; extra == 'gcp'
